[
  {
    "v": 734,
    "vw": 277.7093,
    "a": 277.7093,
    "o": 278.23,
    "c": 277.4,
    "h": 278.23,
    "l": 277.4,
    "t": 1661500800000,
    "n": 24
  },
  {
    "v": 366,
    "vw": 277.6173,
    "a": 277.637,
    "o": 277.6,
    "c": 277.6,
    "h": 277.6,
    "l": 277.6,
    "t": 1661503860000,
    "n": 9
  },
  {
    "v": 501,
    "vw": 277.6938,
    "a": 277.6439,
    "o": 277.7,
    "c": 277.7,
    "h": 277.7,
    "l": 277.7,
    "t": 1661504220000,
    "n": 4
  },
  {
    "v": 476,
    "vw": 277.6992,
    "a": 277.6356,
    "o": 277.7,
    "c": 277.7,
    "h": 277.7,
    "l": 277.7,
    "t": 1661505300000,
    "n": 4
  },
  {
    "v": 116,
    "vw": 277.5005,
    "a": 277.6329,
    "o": 277.51,
    "c": 277.51,
    "h": 277.51,
    "l": 277.51,
    "t": 1661505360000,
    "n": 5
  },
  {
    "v": 203,
    "vw": 277.4221,
    "a": 277.6257,
    "o": 277.42,
    "c": 277.42,
    "h": 277.42,
    "l": 277.42,
    "t": 1661505420000,
    "n": 6
  },
  {
    "v": 756,
    "vw": 277.2107,
    "a": 277.5789,
    "o": 277.2,
    "c": 277.26,
    "h": 277.26,
    "l": 277.2,
    "t": 1661505480000,
    "n": 9
  },
  {
    "v": 240,
    "vw": 276.9913,
    "a": 277.4662,
    "o": 277,
    "c": 277,
    "h": 277,
    "l": 277,
    "t": 1661508660000,
    "n": 5
  },
  {
    "v": 570,
    "vw": 277,
    "a": 277.4363,
    "o": 277,
    "c": 277,
    "h": 277,
    "l": 277,
    "t": 1661508720000,
    "n": 11
  },
  {
    "v": 150,
    "vw": 277.03,
    "a": 277.4295,
    "o": 277.03,
    "c": 277.03,
    "h": 277.03,
    "l": 277.03,
    "t": 1661508780000,
    "n": 1
  },
  {
    "v": 3701,
    "vw": 277.4831,
    "a": 277.4451,
    "o": 277.45,
    "c": 277.5,
    "h": 277.5,
    "l": 277.4,
    "t": 1661508960000,
    "n": 64
  },
  {
    "v": 131,
    "vw": 277.4046,
    "a": 277.4435,
    "o": 277.4,
    "c": 277.4,
    "h": 277.4,
    "l": 277.4,
    "t": 1661509380000,
    "n": 2
  },
  {
    "v": 300,
    "vw": 277.38,
    "a": 277.4388,
    "o": 277.38,
    "c": 277.38,
    "h": 277.38,
    "l": 277.38,
    "t": 1661510880000,
    "n": 3
  },
  {
    "v": 1388,
    "vw": 277.6978,
    "a": 277.4641,
    "o": 277.75,
    "c": 277.74,
    "h": 277.75,
    "l": 277.74,
    "t": 1661511600000,
    "n": 41
  },
  {
    "v": 197,
    "vw": 277.7214,
    "a": 277.4674,
    "o": 277.73,
    "c": 277.73,
    "h": 277.73,
    "l": 277.73,
    "t": 1661511660000,
    "n": 3
  },
  {
    "v": 897,
    "vw": 277.6571,
    "a": 277.4798,
    "o": 277.66,
    "c": 277.65,
    "h": 277.66,
    "l": 277.65,
    "t": 1661511780000,
    "n": 24
  },
  {
    "v": 1579,
    "vw": 277.5253,
    "a": 277.4838,
    "o": 277.5,
    "c": 277.5,
    "h": 277.5,
    "l": 277.5,
    "t": 1661511840000,
    "n": 49
  },
  {
    "v": 336,
    "vw": 277.4149,
    "a": 277.4825,
    "o": 277.43,
    "c": 277.43,
    "h": 277.43,
    "l": 277.43,
    "t": 1661511900000,
    "n": 10
  },
  {
    "v": 878,
    "vw": 277.4442,
    "a": 277.4808,
    "o": 277.38,
    "c": 277.38,
    "h": 277.38,
    "l": 277.38,
    "t": 1661511960000,
    "n": 28
  },
  {
    "v": 2051,
    "vw": 277.3975,
    "a": 277.4728,
    "o": 277.4,
    "c": 277.4,
    "h": 277.4,
    "l": 277.4,
    "t": 1661512020000,
    "n": 21
  },
  {
    "v": 971,
    "vw": 277.2977,
    "a": 277.4652,
    "o": 277.35,
    "c": 277.25,
    "h": 277.35,
    "l": 277.25,
    "t": 1661512080000,
    "n": 25
  },
  {
    "v": 842,
    "vw": 277.2614,
    "a": 277.4528,
    "o": 277.26,
    "c": 277.26,
    "h": 277.26,
    "l": 277.26,
    "t": 1661512200000,
    "n": 18
  },
  {
    "v": 1380,
    "vw": 277.3018,
    "a": 277.4446,
    "o": 277.36,
    "c": 277.26,
    "h": 277.36,
    "l": 277.26,
    "t": 1661512260000,
    "n": 15
  },
  {
    "v": 1722,
    "vw": 277.3392,
    "a": 277.4369,
    "o": 277.34,
    "c": 277.34,
    "h": 277.34,
    "l": 277.34,
    "t": 1661512440000,
    "n": 28
  },
  {
    "v": 1043,
    "vw": 277.3338,
    "a": 277.4331,
    "o": 277.34,
    "c": 277.33,
    "h": 277.34,
    "l": 277.33,
    "t": 1661512500000,
    "n": 21
  },
  {
    "v": 1392,
    "vw": 277.3127,
    "a": 277.4275,
    "o": 277.28,
    "c": 277.34,
    "h": 277.34,
    "l": 277.28,
    "t": 1661512620000,
    "n": 40
  },
  {
    "v": 2643,
    "vw": 277.309,
    "a": 277.4179,
    "o": 277.33,
    "c": 277.3,
    "h": 277.34,
    "l": 277.3,
    "t": 1661512680000,
    "n": 32
  },
  {
    "v": 1367,
    "vw": 277.3221,
    "a": 277.414,
    "o": 277.34,
    "c": 277.34,
    "h": 277.34,
    "l": 277.34,
    "t": 1661512740000,
    "n": 39
  },
  {
    "v": 3036,
    "vw": 277.3402,
    "a": 277.4079,
    "o": 277.34,
    "c": 277.34,
    "h": 277.34,
    "l": 277.34,
    "t": 1661512800000,
    "n": 57
  },
  {
    "v": 2331,
    "vw": 277.3098,
    "a": 277.4021,
    "o": 277.33,
    "c": 277.27,
    "h": 277.34,
    "l": 277.27,
    "t": 1661512860000,
    "n": 44
  },
  {
    "v": 200,
    "vw": 277.4643,
    "a": 277.4024,
    "o": 277.44,
    "c": 277.44,
    "h": 277.44,
    "l": 277.44,
    "t": 1661512920000,
    "n": 5
  },
  {
    "v": 539,
    "vw": 277.3985,
    "a": 277.4023,
    "o": 277.4,
    "c": 277.4,
    "h": 277.4,
    "l": 277.4,
    "t": 1661513280000,
    "n": 20
  },
  {
    "v": 675,
    "vw": 277.4774,
    "a": 277.4035,
    "o": 277.48,
    "c": 277.47,
    "h": 277.48,
    "l": 277.47,
    "t": 1661513340000,
    "n": 18
  },
  {
    "v": 1534,
    "vw": 277.3106,
    "a": 277.4002,
    "o": 277.47,
    "c": 277.23,
    "h": 277.47,
    "l": 277.23,
    "t": 1661513400000,
    "n": 63
  },
  {
    "v": 1196,
    "vw": 277.4072,
    "a": 277.4004,
    "o": 277.4,
    "c": 277.43,
    "h": 277.43,
    "l": 277.4,
    "t": 1661513460000,
    "n": 30
  },
  {
    "v": 102,
    "vw": 277.3009,
    "a": 277.4,
    "o": 277.3,
    "c": 277.3,
    "h": 277.3,
    "l": 277.3,
    "t": 1661514120000,
    "n": 3
  },
  {
    "v": 310,
    "vw": 277.48,
    "a": 277.4004,
    "o": 277.48,
    "c": 277.48,
    "h": 277.48,
    "l": 277.48,
    "t": 1661514360000,
    "n": 6
  },
  {
    "v": 353,
    "vw": 277.5649,
    "a": 277.4017,
    "o": 277.57,
    "c": 277.57,
    "h": 277.57,
    "l": 277.57,
    "t": 1661514420000,
    "n": 15
  },
  {
    "v": 560,
    "vw": 277.5854,
    "a": 277.404,
    "o": 277.58,
    "c": 277.58,
    "h": 277.58,
    "l": 277.58,
    "t": 1661514480000,
    "n": 15
  },
  {
    "v": 593,
    "vw": 277.6811,
    "a": 277.4091,
    "o": 277.67,
    "c": 277.73,
    "h": 277.73,
    "l": 277.67,
    "t": 1661514840000,
    "n": 15
  },
  {
    "v": 1183,
    "vw": 277.7751,
    "a": 277.4182,
    "o": 277.75,
    "c": 277.78,
    "h": 277.78,
    "l": 277.75,
    "t": 1661514900000,
    "n": 40
  },
  {
    "v": 9761,
    "vw": 277.4879,
    "a": 277.4329,
    "o": 277.5505,
    "c": 278.153,
    "h": 278.153,
    "l": 277.2,
    "t": 1661515200000,
    "n": 138
  },
  {
    "v": 1981,
    "vw": 277.7793,
    "a": 277.4444,
    "o": 277.671,
    "c": 277.69,
    "h": 277.69,
    "l": 277.671,
    "t": 1661515260000,
    "n": 23
  },
  {
    "v": 299,
    "vw": 277.8059,
    "a": 277.4462,
    "o": 277.67,
    "c": 277.67,
    "h": 277.67,
    "l": 277.67,
    "t": 1661515320000,
    "n": 41
  },
  {
    "v": 655,
    "vw": 277.5641,
    "a": 277.4478,
    "o": 277.63,
    "c": 277.63,
    "h": 277.63,
    "l": 277.63,
    "t": 1661515440000,
    "n": 25
  },
  {
    "v": 550,
    "vw": 277.6299,
    "a": 277.4507,
    "o": 277.6299,
    "c": 277.6299,
    "h": 277.6299,
    "l": 277.6299,
    "t": 1661515800000,
    "n": 3
  },
  {
    "v": 405,
    "vw": 277.5099,
    "a": 277.4513,
    "o": 277.51,
    "c": 277.51,
    "h": 277.51,
    "l": 277.51,
    "t": 1661516040000,
    "n": 2
  },
  {
    "v": 1041,
    "vw": 277.6246,
    "a": 277.4542,
    "o": 277.58,
    "c": 277.63,
    "h": 277.63,
    "l": 277.58,
    "t": 1661516160000,
    "n": 23
  },
  {
    "v": 823,
    "vw": 277.8112,
    "a": 277.4588,
    "o": 277.8,
    "c": 277.85,
    "h": 277.85,
    "l": 277.8,
    "t": 1661516220000,
    "n": 11
  },
  {
    "v": 144,
    "vw": 277.7632,
    "a": 277.4595,
    "o": 277.8,
    "c": 277.8,
    "h": 277.8,
    "l": 277.8,
    "t": 1661516280000,
    "n": 5
  },
  {
    "v": 159,
    "vw": 277.7922,
    "a": 277.4603,
    "o": 277.77,
    "c": 277.77,
    "h": 277.77,
    "l": 277.77,
    "t": 1661516340000,
    "n": 3
  },
  {
    "v": 665,
    "vw": 277.7938,
    "a": 277.465,
    "o": 277.8,
    "c": 277.8,
    "h": 277.8,
    "l": 277.8,
    "t": 1661516760000,
    "n": 19
  },
  {
    "v": 336,
    "vw": 277.7203,
    "a": 277.4663,
    "o": 277.71,
    "c": 277.71,
    "h": 277.71,
    "l": 277.71,
    "t": 1661516820000,
    "n": 18
  },
  {
    "v": 465,
    "vw": 277.7153,
    "a": 277.4681,
    "o": 277.71,
    "c": 277.71,
    "h": 277.71,
    "l": 277.71,
    "t": 1661516880000,
    "n": 16
  },
  {
    "v": 4995,
    "vw": 278.3658,
    "a": 277.5312,
    "o": 277.83,
    "c": 278.85,
    "h": 278.85,
    "l": 277.83,
    "t": 1661517000000,
    "n": 142
  },
  {
    "v": 2521,
    "vw": 279.0178,
    "a": 277.5821,
    "o": 278.88,
    "c": 278.85,
    "h": 279.15,
    "l": 278.85,
    "t": 1661517060000,
    "n": 70
  },
  {
    "v": 582,
    "vw": 278.5917,
    "a": 277.601,
    "o": 278.59,
    "c": 278.59,
    "h": 278.59,
    "l": 278.59,
    "t": 1661517240000,
    "n": 18
  },
  {
    "v": 349,
    "vw": 278.5182,
    "a": 277.6052,
    "o": 278.56,
    "c": 278.56,
    "h": 278.56,
    "l": 278.56,
    "t": 1661517300000,
    "n": 15
  },
  {
    "v": 3023,
    "vw": 278.4579,
    "a": 277.6381,
    "o": 278.48,
    "c": 278.48,
    "h": 278.48,
    "l": 278.48,
    "t": 1661517360000,
    "n": 85
  },
  {
    "v": 2409,
    "vw": 278.7604,
    "a": 277.677,
    "o": 278.5318,
    "c": 278.84,
    "h": 278.84,
    "l": 278.5318,
    "t": 1661517600000,
    "n": 74
  },
  {
    "v": 7170,
    "vw": 279.0069,
    "a": 277.7848,
    "o": 279,
    "c": 279,
    "h": 279,
    "l": 279,
    "t": 1661517660000,
    "n": 91
  },
  {
    "v": 947,
    "vw": 278.7255,
    "a": 277.7948,
    "o": 278.91,
    "c": 278.6,
    "h": 278.91,
    "l": 278.6,
    "t": 1661517720000,
    "n": 20
  },
  {
    "v": 2586,
    "vw": 278.6533,
    "a": 277.8189,
    "o": 278.63,
    "c": 278.56,
    "h": 278.69,
    "l": 278.55,
    "t": 1661517780000,
    "n": 76
  },
  {
    "v": 2961,
    "vw": 278.4894,
    "a": 277.8398,
    "o": 278.2052,
    "c": 278.8654,
    "h": 278.8654,
    "l": 278.2052,
    "t": 1661517840000,
    "n": 49
  },
  {
    "v": 670,
    "vw": 278.7638,
    "a": 277.8464,
    "o": 278.66,
    "c": 278.79,
    "h": 278.79,
    "l": 278.66,
    "t": 1661517960000,
    "n": 16
  },
  {
    "v": 342,
    "vw": 278.781,
    "a": 277.8497,
    "o": 278.8,
    "c": 278.8,
    "h": 278.8,
    "l": 278.8,
    "t": 1661518020000,
    "n": 6
  },
  {
    "v": 478,
    "vw": 278.7996,
    "a": 277.8544,
    "o": 278.8,
    "c": 278.8,
    "h": 278.8,
    "l": 278.8,
    "t": 1661518080000,
    "n": 17
  },
  {
    "v": 840,
    "vw": 278.7504,
    "a": 277.8622,
    "o": 278.75,
    "c": 278.75,
    "h": 278.75,
    "l": 278.75,
    "t": 1661518140000,
    "n": 9
  },
  {
    "v": 1501,
    "vw": 278.805,
    "a": 277.8812,
    "o": 278.7967,
    "c": 278.8,
    "h": 278.8,
    "l": 278.78,
    "t": 1661518320000,
    "n": 28
  },
  {
    "v": 852,
    "vw": 278.8203,
    "a": 277.8935,
    "o": 278.85,
    "c": 278.85,
    "h": 278.85,
    "l": 278.85,
    "t": 1661518440000,
    "n": 27
  },
  {
    "v": 133,
    "vw": 278.713,
    "a": 278.1957,
    "o": 278.66,
    "c": 278.66,
    "h": 278.66,
    "l": 278.66,
    "t": 1661518560000,
    "n": 4
  },
  {
    "v": 3953,
    "vw": 278.8342,
    "a": 278.2124,
    "o": 278.8,
    "c": 279,
    "h": 279,
    "l": 278.8,
    "t": 1661518620000,
    "n": 55
  },
  {
    "v": 1181,
    "vw": 279.0438,
    "a": 278.2188,
    "o": 279,
    "c": 279.13,
    "h": 279.13,
    "l": 279,
    "t": 1661518680000,
    "n": 32
  },
  {
    "v": 440,
    "vw": 279.1514,
    "a": 278.2215,
    "o": 279.13,
    "c": 279.2,
    "h": 279.2,
    "l": 279.13,
    "t": 1661518740000,
    "n": 12
  },
  {
    "v": 636,
    "vw": 279.2576,
    "a": 278.2258,
    "o": 279.3,
    "c": 279.3,
    "h": 279.3,
    "l": 279.3,
    "t": 1661518800000,
    "n": 26
  },
  {
    "v": 998,
    "vw": 279.2491,
    "a": 278.2324,
    "o": 279.2999,
    "c": 279.3,
    "h": 279.3,
    "l": 279.2999,
    "t": 1661518860000,
    "n": 42
  },
  {
    "v": 10791,
    "vw": 279.3672,
    "a": 278.3081,
    "o": 279.15,
    "c": 279.5,
    "h": 279.5,
    "l": 279.15,
    "t": 1661518980000,
    "n": 117
  },
  {
    "v": 3180,
    "vw": 279.7454,
    "a": 278.3352,
    "o": 279.55,
    "c": 279.8,
    "h": 279.8,
    "l": 279.55,
    "t": 1661519040000,
    "n": 82
  },
  {
    "v": 2532,
    "vw": 280.0367,
    "a": 278.3604,
    "o": 280,
    "c": 280.08,
    "h": 280.1,
    "l": 280,
    "t": 1661519100000,
    "n": 119
  },
  {
    "v": 2841,
    "vw": 280.2454,
    "a": 278.3912,
    "o": 280.35,
    "c": 280.49,
    "h": 280.49,
    "l": 280,
    "t": 1661519160000,
    "n": 80
  },
  {
    "v": 7319,
    "vw": 280.4552,
    "a": 278.4745,
    "o": 280.41,
    "c": 280.5,
    "h": 280.7,
    "l": 280.41,
    "t": 1661519220000,
    "n": 223
  },
  {
    "v": 1963,
    "vw": 280.6813,
    "a": 278.4981,
    "o": 280.7,
    "c": 280.6,
    "h": 280.7,
    "l": 280.6,
    "t": 1661519280000,
    "n": 67
  },
  {
    "v": 1621,
    "vw": 280.689,
    "a": 278.5174,
    "o": 280.58,
    "c": 280.7,
    "h": 280.7,
    "l": 280.58,
    "t": 1661519340000,
    "n": 49
  },
  {
    "v": 1629,
    "vw": 280.4229,
    "a": 278.534,
    "o": 280.45,
    "c": 280.43,
    "h": 280.45,
    "l": 280.43,
    "t": 1661519400000,
    "n": 53
  },
  {
    "v": 908,
    "vw": 280.2761,
    "a": 278.5424,
    "o": 280.2933,
    "c": 280.29,
    "h": 280.2933,
    "l": 280.29,
    "t": 1661519460000,
    "n": 36
  },
  {
    "v": 1400,
    "vw": 280.1489,
    "a": 278.5588,
    "o": 280.27,
    "c": 280.12,
    "h": 280.27,
    "l": 280.04,
    "t": 1661519640000,
    "n": 46
  },
  {
    "v": 1788,
    "vw": 280.2253,
    "a": 278.5743,
    "o": 280.3,
    "c": 280.23,
    "h": 280.3,
    "l": 280.23,
    "t": 1661519700000,
    "n": 53
  },
  {
    "v": 584,
    "vw": 280.1575,
    "a": 278.5792,
    "o": 280.15,
    "c": 280.17,
    "h": 280.17,
    "l": 280.15,
    "t": 1661519760000,
    "n": 11
  },
  {
    "v": 7938,
    "vw": 280.1089,
    "a": 278.64,
    "o": 280.15,
    "c": 280,
    "h": 280.15,
    "l": 280,
    "t": 1661519820000,
    "n": 124
  },
  {
    "v": 3807,
    "vw": 279.9184,
    "a": 278.6639,
    "o": 280,
    "c": 279.91,
    "h": 280.3,
    "l": 279.9,
    "t": 1661519880000,
    "n": 96
  },
  {
    "v": 1666,
    "vw": 279.8488,
    "a": 278.6735,
    "o": 279.9,
    "c": 279.9,
    "h": 279.9,
    "l": 279.9,
    "t": 1661519940000,
    "n": 35
  },
  {
    "v": 1571,
    "vw": 279.5885,
    "a": 278.6827,
    "o": 279.6,
    "c": 279.55,
    "h": 279.6,
    "l": 279.55,
    "t": 1661520060000,
    "n": 62
  },
  {
    "v": 534,
    "vw": 279.4277,
    "a": 278.6846,
    "o": 279.47,
    "c": 279.47,
    "h": 279.47,
    "l": 279.47,
    "t": 1661520120000,
    "n": 21
  },
  {
    "v": 549,
    "vw": 279.6656,
    "a": 278.6872,
    "o": 279.77,
    "c": 279.77,
    "h": 279.77,
    "l": 279.77,
    "t": 1661520180000,
    "n": 15
  },
  {
    "v": 3385,
    "vw": 279.5166,
    "a": 278.7027,
    "o": 279.8,
    "c": 279.31,
    "h": 279.8,
    "l": 279.31,
    "t": 1661520360000,
    "n": 102
  },
  {
    "v": 14382,
    "vw": 279.2162,
    "a": 278.7354,
    "o": 279.3,
    "c": 278.85,
    "h": 279.3,
    "l": 278.8,
    "t": 1661520420000,
    "n": 139
  },
  {
    "v": 334,
    "vw": 278.8746,
    "a": 278.7357,
    "o": 278.9,
    "c": 278.9,
    "h": 278.9,
    "l": 278.9,
    "t": 1661520540000,
    "n": 18
  },
  {
    "v": 266411,
    "vw": 278.916,
    "a": 278.8354,
    "o": 279.08,
    "c": 278.75,
    "h": 279.3,
    "l": 278.75,
    "t": 1661520600000,
    "n": 5075,
    "op": 279.08
  },
  {
    "v": 48863,
    "vw": 278.6976,
    "a": 278.8232,
    "o": 278.66,
    "c": 278.7532,
    "h": 278.86,
    "l": 278.47,
    "t": 1661520660000,
    "n": 1102,
    "op": 279.08
  },
  {
    "v": 43925,
    "vw": 278.5545,
    "a": 278.8034,
    "o": 278.82,
    "c": 278.45,
    "h": 278.82,
    "l": 278.39,
    "t": 1661520720000,
    "n": 871,
    "op": 279.08
  },
  {
    "v": 33207,
    "vw": 278.5278,
    "a": 278.7888,
    "o": 278.44,
    "c": 278.4195,
    "h": 278.7079,
    "l": 278.38,
    "t": 1661520780000,
    "n": 851,
    "op": 279.08
  },
  {
    "v": 34938,
    "vw": 278.6524,
    "a": 278.7817,
    "o": 278.46,
    "c": 278.84,
    "h": 278.8889,
    "l": 278.37,
    "t": 1661520840000,
    "n": 887,
    "op": 279.08
  },
  {
    "v": 56526,
    "vw": 279.038,
    "a": 278.8018,
    "o": 278.842,
    "c": 279.33,
    "h": 279.33,
    "l": 278.7416,
    "t": 1661520900000,
    "n": 1159,
    "op": 279.08
  },
  {
    "v": 65253,
    "vw": 279.2814,
    "a": 278.8416,
    "o": 279.34,
    "c": 279.41,
    "h": 279.48,
    "l": 278.9,
    "t": 1661520960000,
    "n": 1292,
    "op": 279.08
  },
  {
    "v": 37877,
    "vw": 279.2649,
    "a": 278.8611,
    "o": 279.41,
    "c": 279.31,
    "h": 279.415,
    "l": 279.0253,
    "t": 1661521020000,
    "n": 1051,
    "op": 279.08
  },
  {
    "v": 42426,
    "vw": 279.3888,
    "a": 278.887,
    "o": 279.27,
    "c": 279.32,
    "h": 279.52,
    "l": 279.27,
    "t": 1661521080000,
    "n": 773,
    "op": 279.08
  },
  {
    "v": 29975,
    "vw": 279.4159,
    "a": 278.9047,
    "o": 279.3601,
    "c": 279.35,
    "h": 279.5,
    "l": 279.28,
    "t": 1661521140000,
    "n": 968,
    "op": 279.08
  },
  {
    "v": 65894,
    "vw": 279.4045,
    "a": 278.9389,
    "o": 279.41,
    "c": 279.5901,
    "h": 279.6289,
    "l": 279.27,
    "t": 1661521200000,
    "n": 950,
    "op": 279.08
  },
  {
    "v": 38353,
    "vw": 279.6112,
    "a": 278.9647,
    "o": 279.63,
    "c": 279.55,
    "h": 279.7,
    "l": 279.51,
    "t": 1661521260000,
    "n": 691,
    "op": 279.08
  },
  {
    "v": 44888,
    "vw": 279.4419,
    "a": 278.9852,
    "o": 279.5404,
    "c": 279.52,
    "h": 279.545,
    "l": 279.28,
    "t": 1661521320000,
    "n": 663,
    "op": 279.08
  },
  {
    "v": 30982,
    "vw": 279.3816,
    "a": 278.9966,
    "o": 279.51,
    "c": 279.445,
    "h": 279.5525,
    "l": 279.19,
    "t": 1661521380000,
    "n": 639,
    "op": 279.08
  },
  {
    "v": 32396,
    "vw": 279.5586,
    "a": 279.013,
    "o": 279.49,
    "c": 279.37,
    "h": 279.68,
    "l": 279.355,
    "t": 1661521440000,
    "n": 679,
    "op": 279.08
  },
  {
    "v": 51893,
    "vw": 279.2254,
    "a": 279.0225,
    "o": 279.35,
    "c": 279.22,
    "h": 279.5,
    "l": 279.081,
    "t": 1661521500000,
    "n": 832,
    "op": 279.08
  },
  {
    "v": 48964,
    "vw": 278.947,
    "a": 279.0195,
    "o": 279.19,
    "c": 279.035,
    "h": 279.19,
    "l": 278.81,
    "t": 1661521560000,
    "n": 1125,
    "op": 279.08
  },
  {
    "v": 25056,
    "vw": 279.0158,
    "a": 279.0194,
    "o": 279.04,
    "c": 279.005,
    "h": 279.12,
    "l": 278.92,
    "t": 1661521620000,
    "n": 587,
    "op": 279.08
  },
  {
    "v": 37925,
    "vw": 279.2113,
    "a": 279.0251,
    "o": 279.01,
    "c": 279.34,
    "h": 279.35,
    "l": 279.01,
    "t": 1661521680000,
    "n": 759,
    "op": 279.08
  },
  {
    "v": 33324,
    "vw": 279.2452,
    "a": 279.0307,
    "o": 279.33,
    "c": 279.11,
    "h": 279.38,
    "l": 279.08,
    "t": 1661521740000,
    "n": 666,
    "op": 279.08
  },
  {
    "v": 38309,
    "vw": 278.9209,
    "a": 279.0276,
    "o": 279.095,
    "c": 278.56,
    "h": 279.18,
    "l": 278.5428,
    "t": 1661521800000,
    "n": 773,
    "op": 279.08
  },
  {
    "v": 30742,
    "vw": 278.5639,
    "a": 279.0172,
    "o": 278.5443,
    "c": 278.76,
    "h": 278.76,
    "l": 278.4,
    "t": 1661521860000,
    "n": 713,
    "op": 279.08
  },
  {
    "v": 31838,
    "vw": 278.6153,
    "a": 279.0081,
    "o": 278.7411,
    "c": 278.5,
    "h": 278.77,
    "l": 278.461,
    "t": 1661521920000,
    "n": 568,
    "op": 279.08
  },
  {
    "v": 31899,
    "vw": 278.7843,
    "a": 279.0032,
    "o": 278.54,
    "c": 278.89,
    "h": 278.92,
    "l": 278.54,
    "t": 1661521980000,
    "n": 577,
    "op": 279.08
  },
  {
    "v": 15426,
    "vw": 279.0334,
    "a": 279.0035,
    "o": 278.93,
    "c": 279.13,
    "h": 279.18,
    "l": 278.92,
    "t": 1661522040000,
    "n": 432,
    "op": 279.08
  },
  {
    "v": 29472,
    "vw": 279.342,
    "a": 279.0102,
    "o": 279.16,
    "c": 279.54,
    "h": 279.545,
    "l": 279.15,
    "t": 1661522100000,
    "n": 608,
    "op": 279.08
  },
  {
    "v": 27203,
    "vw": 279.5187,
    "a": 279.0194,
    "o": 279.569,
    "c": 279.33,
    "h": 279.63,
    "l": 279.32,
    "t": 1661522160000,
    "n": 483,
    "op": 279.08
  },
  {
    "v": 15285,
    "vw": 279.4257,
    "a": 279.0235,
    "o": 279.36,
    "c": 279.4,
    "h": 279.51,
    "l": 279.345,
    "t": 1661522220000,
    "n": 383,
    "op": 279.08
  },
  {
    "v": 14856,
    "vw": 279.5482,
    "a": 279.0285,
    "o": 279.42,
    "c": 279.58,
    "h": 279.66,
    "l": 279.405,
    "t": 1661522280000,
    "n": 393,
    "op": 279.08
  },
  {
    "v": 29943,
    "vw": 279.5171,
    "a": 279.0378,
    "o": 279.58,
    "c": 279.61,
    "h": 279.65,
    "l": 279.33,
    "t": 1661522340000,
    "n": 541,
    "op": 279.08
  },
  {
    "v": 155536,
    "vw": 279.218,
    "a": 279.0541,
    "o": 279.61,
    "c": 278.94,
    "h": 279.69,
    "l": 278.76,
    "t": 1661522400000,
    "n": 2717,
    "op": 279.08
  },
  {
    "v": 106336,
    "vw": 278.3161,
    "a": 279.0112,
    "o": 278.9,
    "c": 278.19,
    "h": 278.9453,
    "l": 277.9,
    "t": 1661522460000,
    "n": 2361,
    "op": 279.08
  },
  {
    "v": 89988,
    "vw": 277.3351,
    "a": 278.9328,
    "o": 278.23,
    "c": 276.8,
    "h": 278.3,
    "l": 276.71,
    "t": 1661522520000,
    "n": 2178,
    "op": 279.08
  },
  {
    "v": 84681,
    "vw": 277.0343,
    "a": 278.8527,
    "o": 276.81,
    "c": 277.4,
    "h": 277.4,
    "l": 276.6,
    "t": 1661522580000,
    "n": 1532,
    "op": 279.08
  },
  {
    "v": 59652,
    "vw": 277.2082,
    "a": 278.8052,
    "o": 277.42,
    "c": 276.925,
    "h": 277.57,
    "l": 276.84,
    "t": 1661522640000,
    "n": 1029,
    "op": 279.08
  },
  {
    "v": 61572,
    "vw": 277.0015,
    "a": 278.753,
    "o": 277,
    "c": 276.98,
    "h": 277.37,
    "l": 276.7,
    "t": 1661522700000,
    "n": 1331,
    "op": 279.08
  },
  {
    "v": 86533,
    "vw": 277.1614,
    "a": 278.6908,
    "o": 277,
    "c": 277.45,
    "h": 277.47,
    "l": 276.84,
    "t": 1661522760000,
    "n": 1053,
    "op": 279.08
  },
  {
    "v": 101176,
    "vw": 277.7467,
    "a": 278.6496,
    "o": 277.46,
    "c": 277.94,
    "h": 278.085,
    "l": 277.46,
    "t": 1661522820000,
    "n": 1048,
    "op": 279.08
  },
  {
    "v": 45204,
    "vw": 277.7628,
    "a": 278.6326,
    "o": 277.9,
    "c": 277.68,
    "h": 277.97,
    "l": 277.5801,
    "t": 1661522880000,
    "n": 769,
    "op": 279.08
  },
  {
    "v": 141496,
    "vw": 278.8453,
    "a": 278.6446,
    "o": 277.7,
    "c": 279.84,
    "h": 279.84,
    "l": 277.6671,
    "t": 1661522940000,
    "n": 2298,
    "op": 279.08
  },
  {
    "v": 368782,
    "vw": 279.2578,
    "a": 278.7234,
    "o": 279.81,
    "c": 279.47,
    "h": 280.34,
    "l": 278.85,
    "t": 1661523000000,
    "n": 2457,
    "op": 279.08
  },
  {
    "v": 64611,
    "vw": 279.2672,
    "a": 278.7354,
    "o": 279.49,
    "c": 279.07,
    "h": 279.495,
    "l": 279.0573,
    "t": 1661523060000,
    "n": 1093,
    "op": 279.08
  },
  {
    "v": 53054,
    "vw": 279.0779,
    "a": 278.7414,
    "o": 279.06,
    "c": 279.65,
    "h": 279.65,
    "l": 278.5701,
    "t": 1661523120000,
    "n": 1104,
    "op": 279.08
  },
  {
    "v": 87470,
    "vw": 279.1866,
    "a": 278.7541,
    "o": 279.6227,
    "c": 278.9199,
    "h": 279.8,
    "l": 278.78,
    "t": 1661523180000,
    "n": 940,
    "op": 279.08
  },
  {
    "v": 40949,
    "vw": 279.1428,
    "a": 278.7592,
    "o": 278.92,
    "c": 279.15,
    "h": 279.35,
    "l": 278.92,
    "t": 1661523240000,
    "n": 794,
    "op": 279.08
  },
  {
    "v": 40536,
    "vw": 279.0456,
    "a": 278.7629,
    "o": 279.23,
    "c": 278.65,
    "h": 279.41,
    "l": 278.6,
    "t": 1661523300000,
    "n": 791,
    "op": 279.08
  },
  {
    "v": 38704,
    "vw": 278.5192,
    "a": 278.7599,
    "o": 278.66,
    "c": 278.69,
    "h": 278.79,
    "l": 278.24,
    "t": 1661523360000,
    "n": 788,
    "op": 279.08
  },
  {
    "v": 42187,
    "vw": 278.6715,
    "a": 278.7588,
    "o": 278.7,
    "c": 278.6376,
    "h": 278.8404,
    "l": 278.48,
    "t": 1661523420000,
    "n": 795,
    "op": 279.08
  },
  {
    "v": 35774,
    "vw": 278.759,
    "a": 278.7588,
    "o": 278.69,
    "c": 278.9402,
    "h": 279.12,
    "l": 278.48,
    "t": 1661523480000,
    "n": 736,
    "op": 279.08
  },
  {
    "v": 17877,
    "vw": 278.8041,
    "a": 278.759,
    "o": 278.805,
    "c": 278.79,
    "h": 278.9,
    "l": 278.7,
    "t": 1661523540000,
    "n": 424,
    "op": 279.08
  }
]
